<?xml version="1.0" encoding="UTF-8" standalone="yes"?>
<RepoProduct>
    <productList>
        <entry>
            <key>4</key>
            <value identificador="4">
                <Name>Nintendo</Name>
                <price>34.0</price>
                <description>Feo</description>
            </value>
        </entry>
        <entry>
            <key>8</key>
            <value identificador="8">
                <Name>PLay</Name>
                <price>56.0</price>
                <description>Guapo</description>
            </value>
        </entry>
        <entry>
            <key>10</key>
            <value identificador="10">
                <Name>PC</Name>
                <price>1.0</price>
                <description>Mierda</description>
            </value>
        </entry>
    </productList>
</RepoProduct>
